neuron_model_templates/__init__.py
neuron_model_templates/rate_neurons/__init__.py
neuron_model_templates/rate_neurons/leaky_integrator.yaml
neuron_model_templates/spiking_neurons/__init__.py
neuron_model_templates/spiking_neurons/ik.yaml
neuron_model_templates/spiking_neurons/lif.yaml
neuron_model_templates/spiking_neurons/qif.yaml
rectipy/__init__.py
rectipy/edges.py
rectipy/network.py
rectipy/nodes.py
rectipy/observer.py
rectipy/utility.py
rectipy_tests/__init__.py
rectipy_tests/test_edges.py
rectipy_tests/test_network.py
rectipy_tests/test_nodes.py
rectipy-0.12.2.dist-info/LICENSE
rectipy-0.12.2.dist-info/METADATA
rectipy-0.12.2.dist-info/WHEEL
rectipy-0.12.2.dist-info/top_level.txt
rectipy-0.12.2.dist-info/RECORD
