Metadata-Version: 2.1
Name: rectipy
Version: 0.12.2
Summary: Recurrent neural network training in Python
Home-page: UNKNOWN
Author: Richard Gast
Author-email: richard.gast@northwestern.edu
License: GPL v3
Platform: UNKNOWN
Classifier: Programming Language :: Python :: 3
Classifier: Programming Language :: Python :: 3.8
Classifier: Programming Language :: Python :: 3.9
Classifier: Programming Language :: Python :: 3.10
Classifier: Programming Language :: Python :: 3.11
Classifier: Programming Language :: Python :: 3.12
Classifier: License :: OSI Approved :: GNU General Public License v3 (GPLv3)
Classifier: Operating System :: OS Independent
Classifier: Development Status :: 3 - Alpha
Classifier: Intended Audience :: Developers
Classifier: Intended Audience :: Science/Research
Classifier: Topic :: Scientific/Engineering
Requires-Python: >=3.8
License-File: LICENSE
Requires-Dist: torch
Requires-Dist: pyrates
Requires-Dist: numpy
Requires-Dist: matplotlib
Requires-Dist: scipy
Requires-Dist: pandas
Requires-Dist: multipledispatch
Provides-Extra: dev
Requires-Dist: pytest; extra == "dev"
Requires-Dist: bump2version; extra == "dev"
